rraider/BlackScholes.py
rraider/__init__.py
rraider/data.py
rraider/estimate.py
rraider/portfolio.py
rraider/pricing.py
rraider/risk.py
rraider/simulate.py
rraider/utils.py
rraider-0.1.0.dist-info/LICENSE
rraider-0.1.0.dist-info/METADATA
rraider-0.1.0.dist-info/WHEEL
rraider-0.1.0.dist-info/top_level.txt
rraider-0.1.0.dist-info/RECORD
